baseband_insider/__init__.py
baseband_insider/context.py
baseband_insider/protocol.py
baseband_insider/server.py
baseband_insider/utils.py
baseband_insider-0.0.2.dist-info/METADATA
baseband_insider-0.0.2.dist-info/WHEEL
baseband_insider-0.0.2.dist-info/top_level.txt
baseband_insider-0.0.2.dist-info/RECORD
