Metadata-Version: 2.4
Name: baseband_insider
Version: 0.0.2
Summary: Temporary protocol helpers for building event streams
Requires-Python: >=3.10
Requires-Dist: websockets~=12.0
